poppy_humanoid/__init__.py
poppy_humanoid/_version.py
poppy_humanoid/poppy_humanoid.py
poppy_humanoid/configuration/poppy_humanoid.json
poppy_humanoid/media/sounds/error.wav
poppy_humanoid/primitives/__init__.py
poppy_humanoid/primitives/dance.py
poppy_humanoid/primitives/idle.py
poppy_humanoid/primitives/interaction.py
poppy_humanoid/primitives/posture.py
poppy_humanoid/primitives/safe.py
poppy_humanoid/utils/__init__.py
poppy_humanoid/vrep-scene/poppy_humanoid.ttt
poppy_humanoid-3.0.0.dist-info/LICENSE
poppy_humanoid-3.0.0.dist-info/METADATA
poppy_humanoid-3.0.0.dist-info/WHEEL
poppy_humanoid-3.0.0.dist-info/top_level.txt
poppy_humanoid-3.0.0.dist-info/RECORD
